src/hdl/test.vhd
library IEEE;
use IEEE.std_logic_1164.all;
-- use IEEE.float_pkg.all;

library IEEE_PROPOSED;
use IEEE_PROPOSED.float_pkg.all;


entity test is
    port (
        a, b: in float32;
        c: out float32
    );
end entity;


architecture Behavioral of test is
begin
    c <= a + b;
end architecture;

src/tb/test_tb.vhd
library IEEE;
use IEEE.std_logic_1164.all;
-- use IEEE.float_pkg.all;

library IEEE_PROPOSED;
use IEEE_PROPOSED.float_pkg.all;


entity test_tb is
end entity;

architecture Behavioral of test_tb is
    component test is
        port (
            a, b: in float32;
            c: out float32
        );
    end component;

    signal a, b, c: float32 := to_float32(to_float(0.0));
begin
    uut: test port map (
        a => a,
        b => b,
        c => c
    );

    process is
    begin
        a <= a + to_float32(to_float(3.21));
        b <= b - to_float32(to_float(1.23));
        wait for 10 ns;
    end process;
end architecture;

ghdl_sim/out.vcd
$date
  Thu Apr  6 18:38:32 2023
$end
$version
  GHDL v0
$end
$timescale
  1 fs
$end
$scope module standard $end
$upscope $end
$scope module textio $end
$upscope $end
$scope module std_logic_1164 $end
$upscope $end
$scope module fixed_float_types $end
$upscope $end
$scope module numeric_std $end
$upscope $end
$scope module math_real $end
$upscope $end
$scope module test_tb $end
$var reg 32 ! a[8:-23] $end
$var reg 32 " b[8:-23] $end
$var reg 32 # c[8:-23] $end
$scope module uut $end
$var reg 32 $ a[8:-23] $end
$var reg 32 % b[8:-23] $end
$var reg 32 & c[8:-23] $end
$upscope $end
$upscope $end
$enddefinitions $end
#0
b01000000010011010111000010100100 !
b10111111100111010111000010100100 "
b00111111111111010111000010100100 #
b01000000010011010111000010100100 $
b10111111100111010111000010100100 %
b00111111111111010111000010100100 &
#10000000
b01000000110011010111000010100100 !
b11000000000111010111000010100100 "
b01000000011111010111000010100100 #
b01000000110011010111000010100100 $
b11000000000111010111000010100100 %
b01000000011111010111000010100100 &
#20000000
b01000001000110100001010001111011 !
b11000000011011000010100011110110 "
b01000000101111100001010001111011 #
b01000001000110100001010001111011 $
b11000000011011000010100011110110 %
b01000000101111100001010001111011 &
#30000000
b01000001010011010111000010100100 !
b11000000100111010111000010100100 "
b01000000111111010111000010100100 #
b01000001010011010111000010100100 $
b11000000100111010111000010100100 %
b01000000111111010111000010100100 &
#40000000
b01000001100000000110011001100110 !
b11000000110001001100110011001101 "
b01000001000111100110011001100110 #
b01000001100000000110011001100110 $
b11000000110001001100110011001101 %
b01000001000111100110011001100110 &
#50000000
b01000001100110100001010001111010 !
b11000000111011000010100011110110 "
b01000001001111100001010001111001 #
b01000001100110100001010001111010 $
b11000000111011000010100011110110 %
b01000001001111100001010001111001 &
#60000000
b01000001101100111100001010001110 !
b11000001000010011100001010010000 "
b01000001010111011100001010001100 #
b01000001101100111100001010001110 $
b11000001000010011100001010010000 %
b01000001010111011100001010001100 &
#70000000
b01000001110011010111000010100010 !
b11000001000111010111000010100100 "
b01000001011111010111000010100000 #
b01000001110011010111000010100010 $
b11000001000111010111000010100100 %
b01000001011111010111000010100000 &
#80000000
b01000001111001110001111010110110 !
b11000001001100010001111010111000 "
b01000001100011101000111101011010 #
b01000001111001110001111010110110 $
b11000001001100010001111010111000 %
b01000001100011101000111101011010 &
#90000000
b01000010000000000110011001100101 !
b11000001010001001100110011001100 "
b01000001100111100110011001100100 #
b01000010000000000110011001100101 $
b11000001010001001100110011001100 %
b01000001100111100110011001100100 &
#100000000
b01000010000011010011110101101111 !
b11000001010110000111101011100000 "
b01000001101011100011110101101110 #
b01000010000011010011110101101111 $
b11000001010110000111101011100000 %
b01000001101011100011110101101110 &
